SSVDpkg_663proj21S/SSVDversion1.py
SSVDpkg_663proj21S/SSVDversion2.py
SSVDpkg_663proj21S/SSVDversion3.py
SSVDpkg_663proj21S/SSVDversion4.py
SSVDpkg_663proj21S/SSVDversion5.py
SSVDpkg_663proj21S/__init__.py
SSVDpkg_663proj21S/functions.py
SSVDpkg_663proj21S-0.1.dist-info/LICENSE
SSVDpkg_663proj21S-0.1.dist-info/METADATA
SSVDpkg_663proj21S-0.1.dist-info/WHEEL
SSVDpkg_663proj21S-0.1.dist-info/top_level.txt
SSVDpkg_663proj21S-0.1.dist-info/RECORD
